{"ts": 1774589491.1504579, "data": [{"date": "2021-01-01", "stock_id": "2633", "country": "Taiwan", "revenue": 3933903000, "revenue_month": 12, "revenue_year": 2020}, {"date": "2021-02-01", "stock_id": "2633", "country": "Taiwan", "revenue": 3148933000, "revenue_month": 1, "revenue_year": 2021}, {"date": "2021-03-01", "stock_id": "2633", "country": "Taiwan", "revenue": 3247104000, "revenue_month": 2, "revenue_year": 2021}, {"date": "2021-04-01", "stock_id": "2633", "country": "Taiwan", "revenue": 3471325000, "revenue_month": 3, "revenue_year": 2021}, {"date": "2021-05-01", "stock_id": "2633", "country": "Taiwan", "revenue": 3798528000, "revenue_month": 4, "revenue_year": 2021}, {"date": "2021-06-01", "stock_id": "2633", "country": "Taiwan", "revenue": 1901903000, "revenue_month": 5, "revenue_year": 2021}, {"date": "2021-07-01", "stock_id": "2633", "country": "Taiwan", "revenue": 401290000, "revenue_month": 6, "revenue_year": 2021}, {"date": "2021-08-01", "stock_id": "2633", "country": "Taiwan", "revenue": 840306000, "revenue_month": 7, "revenue_year": 2021}, {"date": "2021-09-01", "stock_id": "2633", "country": "Taiwan", "revenue": 1621143000, "revenue_month": 8, "revenue_year": 2021}, {"date": "2021-10-01", "stock_id": "2633", "country": "Taiwan", "revenue": 2146949000, "revenue_month": 9, "revenue_year": 2021}, {"date": "2021-11-01", "stock_id": "2633", "country": "Taiwan", "revenue": 2832491000, "revenue_month": 10, "revenue_year": 2021}, {"date": "2021-12-01", "stock_id": "2633", "country": "Taiwan", "revenue": 3068202000, "revenue_month": 11, "revenue_year": 2021}, {"date": "2022-01-01", "stock_id": "2633", "country": "Taiwan", "revenue": 3749713000, "revenue_month": 12, "revenue_year": 2021}, {"date": "2022-02-01", "stock_id": "2633", "country": "Taiwan", "revenue": 2950990000, "revenue_month": 1, "revenue_year": 2022}, {"date": "2022-03-01", "stock_id": "2633", "country": "Taiwan", "revenue": 2817257000, "revenue_month": 2, "revenue_year": 2022}, {"date": "2022-04-01", "stock_id": "2633", "country": "Taiwan", "revenue": 3222095000, "revenue_month": 3, "revenue_year": 2022}, {"date": "2022-05-01", "stock_id": "2633", "country": "Taiwan", "revenue": 2748579000, "revenue_month": 4, "revenue_year": 2022}, {"date": "2022-06-01", "stock_id": "2633", "country": "Taiwan", "revenue": 1790496000, "revenue_month": 5, "revenue_year": 2022}, {"date": "2022-07-01", "stock_id": "2633", "country": "Taiwan", "revenue": 2126536000, "revenue_month": 6, "revenue_year": 2022}, {"date": "2022-08-01", "stock_id": "2633", "country": "Taiwan", "revenue": 2991101000, "revenue_month": 7, "revenue_year": 2022}, {"date": "2022-09-01", "stock_id": "2633", "country": "Taiwan", "revenue": 3366023000, "revenue_month": 8, "revenue_year": 2022}, {"date": "2022-10-01", "stock_id": "2633", "country": "Taiwan", "revenue": 3423080000, "revenue_month": 9, "revenue_year": 2022}, {"date": "2022-11-01", "stock_id": "2633", "country": "Taiwan", "revenue": 3697609000, "revenue_month": 10, "revenue_year": 2022}, {"date": "2022-12-01", "stock_id": "2633", "country": "Taiwan", "revenue": 3753298000, "revenue_month": 11, "revenue_year": 2022}, {"date": "2023-01-01", "stock_id": "2633", "country": "Taiwan", "revenue": 4246169000, "revenue_month": 12, "revenue_year": 2022}, {"date": "2023-02-01", "stock_id": "2633", "country": "Taiwan", "revenue": 4344539000, "revenue_month": 1, "revenue_year": 2023}, {"date": "2023-03-01", "stock_id": "2633", "country": "Taiwan", "revenue": 3729498000, "revenue_month": 2, "revenue_year": 2023}, {"date": "2023-04-01", "stock_id": "2633", "country": "Taiwan", "revenue": 4074508000, "revenue_month": 3, "revenue_year": 2023}, {"date": "2023-05-01", "stock_id": "2633", "country": "Taiwan", "revenue": 4294450000, "revenue_month": 4, "revenue_year": 2023}, {"date": "2023-06-01", "stock_id": "2633", "country": "Taiwan", "revenue": 3995200000, "revenue_month": 5, "revenue_year": 2023}, {"date": "2023-07-01", "stock_id": "2633", "country": "Taiwan", "revenue": 4019151000, "revenue_month": 6, "revenue_year": 2023}, {"date": "2023-08-01", "stock_id": "2633", "country": "Taiwan", "revenue": 4069922000, "revenue_month": 7, "revenue_year": 2023}, {"date": "2023-09-01", "stock_id": "2633", "country": "Taiwan", "revenue": 4202652000, "revenue_month": 8, "revenue_year": 2023}, {"date": "2023-10-01", "stock_id": "2633", "country": "Taiwan", "revenue": 3916585000, "revenue_month": 9, "revenue_year": 2023}, {"date": "2023-11-01", "stock_id": "2633", "country": "Taiwan", "revenue": 4396204000, "revenue_month": 10, "revenue_year": 2023}, {"date": "2023-12-01", "stock_id": "2633", "country": "Taiwan", "revenue": 4240843000, "revenue_month": 11, "revenue_year": 2023}, {"date": "2024-01-01", "stock_id": "2633", "country": "Taiwan", "revenue": 4528471000, "revenue_month": 12, "revenue_year": 2023}, {"date": "2024-02-01", "stock_id": "2633", "country": "Taiwan", "revenue": 4296910000, "revenue_month": 1, "revenue_year": 2024}, {"date": "2024-03-01", "stock_id": "2633", "country": "Taiwan", "revenue": 4496773000, "revenue_month": 2, "revenue_year": 2024}, {"date": "2024-04-01", "stock_id": "2633", "country": "Taiwan", "revenue": 4584589000, "revenue_month": 3, "revenue_year": 2024}, {"date": "2024-05-01", "stock_id": "2633", "country": "Taiwan", "revenue": 4409676000, "revenue_month": 4, "revenue_year": 2024}, {"date": "2024-06-01", "stock_id": "2633", "country": "Taiwan", "revenue": 4311959000, "revenue_month": 5, "revenue_year": 2024}, {"date": "2024-07-01", "stock_id": "2633", "country": "Taiwan", "revenue": 4402938000, "revenue_month": 6, "revenue_year": 2024}, {"date": "2024-08-01", "stock_id": "2633", "country": "Taiwan", "revenue": 4241087000, "revenue_month": 7, "revenue_year": 2024}, {"date": "2024-09-01", "stock_id": "2633", "country": "Taiwan", "revenue": 4549657000, "revenue_month": 8, "revenue_year": 2024}, {"date": "2024-10-01", "stock_id": "2633", "country": "Taiwan", "revenue": 4456901000, "revenue_month": 9, "revenue_year": 2024}, {"date": "2024-11-01", "stock_id": "2633", "country": "Taiwan", "revenue": 4120049000, "revenue_month": 10, "revenue_year": 2024}, {"date": "2024-12-01", "stock_id": "2633", "country": "Taiwan", "revenue": 4516576000, "revenue_month": 11, "revenue_year": 2024}, {"date": "2025-01-01", "stock_id": "2633", "country": "Taiwan", "revenue": 4798549000, "revenue_month": 12, "revenue_year": 2024}, {"date": "2025-02-01", "stock_id": "2633", "country": "Taiwan", "revenue": 4660942000, "revenue_month": 1, "revenue_year": 2025}, {"date": "2025-03-01", "stock_id": "2633", "country": "Taiwan", "revenue": 4122096000, "revenue_month": 2, "revenue_year": 2025}, {"date": "2025-04-01", "stock_id": "2633", "country": "Taiwan", "revenue": 4590596000, "revenue_month": 3, "revenue_year": 2025}, {"date": "2025-05-01", "stock_id": "2633", "country": "Taiwan", "revenue": 4516131000, "revenue_month": 4, "revenue_year": 2025}, {"date": "2025-06-01", "stock_id": "2633", "country": "Taiwan", "revenue": 4551587000, "revenue_month": 5, "revenue_year": 2025}, {"date": "2025-07-01", "stock_id": "2633", "country": "Taiwan", "revenue": 4293173000, "revenue_month": 6, "revenue_year": 2025}, {"date": "2025-08-01", "stock_id": "2633", "country": "Taiwan", "revenue": 4386143000, "revenue_month": 7, "revenue_year": 2025}, {"date": "2025-09-01", "stock_id": "2633", "country": "Taiwan", "revenue": 4751344000, "revenue_month": 8, "revenue_year": 2025}, {"date": "2025-10-01", "stock_id": "2633", "country": "Taiwan", "revenue": 4236093000, "revenue_month": 9, "revenue_year": 2025}, {"date": "2025-11-01", "stock_id": "2633", "country": "Taiwan", "revenue": 4969772000, "revenue_month": 10, "revenue_year": 2025}, {"date": "2025-12-01", "stock_id": "2633", "country": "Taiwan", "revenue": 4673729000, "revenue_month": 11, "revenue_year": 2025}, {"date": "2026-01-01", "stock_id": "2633", "country": "Taiwan", "revenue": 4896850000, "revenue_month": 12, "revenue_year": 2025}, {"date": "2026-02-01", "stock_id": "2633", "country": "Taiwan", "revenue": 4422943000, "revenue_month": 1, "revenue_year": 2026}, {"date": "2026-03-01", "stock_id": "2633", "country": "Taiwan", "revenue": 4672521000, "revenue_month": 2, "revenue_year": 2026}]}